iota_auth/__init__.py
iota_auth/admin.py
iota_auth/apps.py
iota_auth/backend.py
iota_auth/forms.py
iota_auth/models.py
iota_auth/seed_validation.py
iota_auth/urls.py
iota_auth/utils.py
iota_auth/views.py
iota_auth-0.1.8.dist-info/DESCRIPTION.rst
iota_auth-0.1.8.dist-info/METADATA
iota_auth-0.1.8.dist-info/RECORD
iota_auth-0.1.8.dist-info/WHEEL
iota_auth-0.1.8.dist-info/metadata.json
iota_auth-0.1.8.dist-info/top_level.txt
