Metadata-Version: 2.0
Name: iota-auth
Version: 0.1.8
Summary: A custom authentication backend for Django Users to connect to the IOTA Tangle.
Home-page: https://github.com/davidjguinane/django-iota-auth
Author: David Guinane
Author-email: david.j.guinane@gmail.com
License: UNKNOWN
Download-URL: https://github.com/davidjguinane/django-iota-auth/archive/0.1.8.tar.gz
Keywords: iota,django,authentication
Platform: UNKNOWN
Classifier: Development Status :: 4 - Beta
Classifier: Environment :: Web Environment
Classifier: Framework :: Django
Classifier: Framework :: Django :: 2.0
Classifier: Natural Language :: English
Classifier: Intended Audience :: Developers
Classifier: License :: OSI Approved :: GNU General Public License v3 (GPLv3)
Classifier: Operating System :: OS Independent
Classifier: Programming Language :: Python
Classifier: Programming Language :: Python :: 3.6
Requires-Dist: django-encrypted-cookie-session (>=3.2.0)
Requires-Dist: pyota (>=2.0.3)
